jupytab_server/__init__.py
jupytab_server/__version__.py
jupytab_server/jupytab.py
jupytab_server/jupytab_api.py
jupytab_server/kernel_executor.py
jupytab_server/log_pipe.py
jupytab_server/structures.py
jupytab_server/static/favicon.ico
jupytab_server/static/index.html
jupytab_server/static/notebook.js
jupytab_server/static/vendor/bootstrap/bootstrap-4.2.1.min.css
jupytab_server/static/vendor/bootstrap/bootstrap-4.2.1.min.js
jupytab_server/static/vendor/jquery/jquery-3.3.1.min.js
jupytab_server/static/vendor/popper/popper-1.14.6.min.js
jupytab_server/static/vendor/tableau/tableauwdc-2.3.latest.js
tests/__init__.py
tests/test_config.py
tests/test_nb_run.py
jupytab_server-0.9.11.dist-info/METADATA
jupytab_server-0.9.11.dist-info/WHEEL
jupytab_server-0.9.11.dist-info/entry_points.txt
jupytab_server-0.9.11.dist-info/top_level.txt
jupytab_server-0.9.11.dist-info/RECORD
