Metadata-Version: 2.1
Name: jupytab-server
Version: 0.9.11
Summary: Connect Tableau to your Jupyter Notebook
Home-page: https://github.com/CFMTech/Jupytab
Author: Brian Tribondeau
Author-email: brian.tribondeau@cfm.fr
License: MIT
Project-URL: Bug Tracker, https://github.com/CFMTech/Jupytab/issues
Project-URL: Documentation, https://github.com/CFMTech/Jupytab
Project-URL: Source Code, https://github.com/CFMTech/Jupytab
Keywords: jupytab jupyter notebook wdc tableau
Platform: UNKNOWN
Classifier: License :: OSI Approved :: MIT License
Classifier: Programming Language :: Python :: 3
Classifier: Programming Language :: Python :: 3.7
Requires-Python: >=3.6
Requires-Dist: jupyter-kernel-gateway
